{
  "timestamp": "2026-04-13 16:53:43",
  "portfolio_start": "2025-08-18",
  "reshuffle_date": "2026-02-25",
  "days_held": 238,
  "years_held": 0.65,
  "original_capital": 85187.0,
  "total_cost_basis": 119000.45,
  "total_value": 118250.68,
  "total_gain": 33063.68,
  "total_gain_pct": 38.81,
  "gain_vs_basis": -749.77,
  "gain_vs_basis_pct": -0.63,
  "cagr": 65.42,
  "num_stocks": 14,
  "holdings": [
    {
      "ticker": "NVDA",
      "score": 85.1,
      "shares": 47,
      "avg_cost": 184.59,
      "cost_basis": 8675.7,
      "current_price": 188.17,
      "current_value": 8843.76,
      "gain_loss": 168.06,
      "gain_pct": 1.94,
      "weight": 7.48,
      "target_weight": 7.14
    },
    {
      "ticker": "V",
      "score": 79.3,
      "shares": 26,
      "avg_cost": 311.54,
      "cost_basis": 8100.0,
      "current_price": 306.95,
      "current_value": 7980.83,
      "gain_loss": -119.17,
      "gain_pct": -1.47,
      "weight": 6.75,
      "target_weight": 7.14
    },
    {
      "ticker": "LLY",
      "score": 79.1,
      "shares": 8,
      "avg_cost": 1033.32,
      "cost_basis": 8266.56,
      "current_price": 929.54,
      "current_value": 7436.32,
      "gain_loss": -830.24,
      "gain_pct": -10.04,
      "weight": 6.29,
      "target_weight": 7.14
    },
    {
      "ticker": "MA",
      "score": 78.7,
      "shares": 16,
      "avg_cost": 508.4,
      "cost_basis": 8134.48,
      "current_price": 503.27,
      "current_value": 8052.32,
      "gain_loss": -82.16,
      "gain_pct": -1.01,
      "weight": 6.81,
      "target_weight": 7.14
    },
    {
      "ticker": "NOW",
      "score": 78.4,
      "shares": 81,
      "avg_cost": 103.57,
      "cost_basis": 8389.0,
      "current_price": 88.76,
      "current_value": 7189.56,
      "gain_loss": -1199.44,
      "gain_pct": -14.3,
      "weight": 6.08,
      "target_weight": 7.14
    },
    {
      "ticker": "AVGO",
      "score": 73.9,
      "shares": 25,
      "avg_cost": 332.23,
      "cost_basis": 8305.63,
      "current_price": 377.05,
      "current_value": 9426.25,
      "gain_loss": 1120.62,
      "gain_pct": 13.49,
      "weight": 7.97,
      "target_weight": 7.14
    },
    {
      "ticker": "ADBE",
      "score": 73.8,
      "shares": 32,
      "avg_cost": 254.91,
      "cost_basis": 8157.0,
      "current_price": 237.52,
      "current_value": 7600.64,
      "gain_loss": -556.36,
      "gain_pct": -6.82,
      "weight": 6.43,
      "target_weight": 7.14
    },
    {
      "ticker": "MSFT",
      "score": 71.9,
      "shares": 21,
      "avg_cost": 493.44,
      "cost_basis": 10362.26,
      "current_price": 381.02,
      "current_value": 8001.42,
      "gain_loss": -2360.84,
      "gain_pct": -22.78,
      "weight": 6.77,
      "target_weight": 7.14
    },
    {
      "ticker": "GOOGL",
      "score": 71.5,
      "shares": 26,
      "avg_cost": 249.88,
      "cost_basis": 6497.0,
      "current_price": 319.83,
      "current_value": 8315.58,
      "gain_loss": 1818.58,
      "gain_pct": 27.99,
      "weight": 7.03,
      "target_weight": 7.14
    },
    {
      "ticker": "META",
      "score": 71.2,
      "shares": 12,
      "avg_cost": 746.88,
      "cost_basis": 8962.6,
      "current_price": 630.05,
      "current_value": 7560.6,
      "gain_loss": -1402.0,
      "gain_pct": -15.64,
      "weight": 6.39,
      "target_weight": 7.14
    },
    {
      "ticker": "CRM",
      "score": 69.1,
      "shares": 44,
      "avg_cost": 189.25,
      "cost_basis": 8327.0,
      "current_price": 173.25,
      "current_value": 7623.0,
      "gain_loss": -704.0,
      "gain_pct": -8.45,
      "weight": 6.45,
      "target_weight": 7.14
    },
    {
      "ticker": "AAPL",
      "score": 66.9,
      "shares": 30,
      "avg_cost": 273.47,
      "cost_basis": 8204.0,
      "current_price": 257.86,
      "current_value": 7735.8,
      "gain_loss": -468.2,
      "gain_pct": -5.71,
      "weight": 6.54,
      "target_weight": 7.14
    },
    {
      "ticker": "NFLX",
      "score": 66.7,
      "shares": 125,
      "avg_cost": 81.99,
      "cost_basis": 10248.22,
      "current_price": 103.48,
      "current_value": 12935.0,
      "gain_loss": 2686.78,
      "gain_pct": 26.22,
      "weight": 10.94,
      "target_weight": 7.14
    },
    {
      "ticker": "AMZN",
      "score": 63.3,
      "shares": 40,
      "avg_cost": 209.28,
      "cost_basis": 8371.0,
      "current_price": 238.74,
      "current_value": 9549.6,
      "gain_loss": 1178.6,
      "gain_pct": 14.08,
      "weight": 8.08,
      "target_weight": 7.14
    }
  ]
}