{
  "timestamp": "2026-04-09 18:49:46",
  "portfolio_start": "2025-08-18",
  "reshuffle_date": "2026-02-25",
  "days_held": 234,
  "years_held": 0.64,
  "original_capital": 85187.0,
  "total_cost_basis": 119000.45,
  "total_value": 116643.74,
  "total_gain": 31456.74,
  "total_gain_pct": 36.93,
  "gain_vs_basis": -2356.71,
  "gain_vs_basis_pct": -1.98,
  "cagr": 63.32,
  "num_stocks": 14,
  "holdings": [
    {
      "ticker": "NVDA",
      "score": 85.1,
      "shares": 47,
      "avg_cost": 184.59,
      "cost_basis": 8675.7,
      "current_price": 183.46,
      "current_value": 8622.67,
      "gain_loss": -53.03,
      "gain_pct": -0.61,
      "weight": 7.39,
      "target_weight": 7.14
    },
    {
      "ticker": "V",
      "score": 79.3,
      "shares": 26,
      "avg_cost": 311.54,
      "cost_basis": 8100.0,
      "current_price": 307.76,
      "current_value": 8001.63,
      "gain_loss": -98.37,
      "gain_pct": -1.21,
      "weight": 6.86,
      "target_weight": 7.14
    },
    {
      "ticker": "LLY",
      "score": 79.1,
      "shares": 8,
      "avg_cost": 1033.32,
      "cost_basis": 8266.56,
      "current_price": 957.24,
      "current_value": 7657.92,
      "gain_loss": -608.64,
      "gain_pct": -7.36,
      "weight": 6.57,
      "target_weight": 7.14
    },
    {
      "ticker": "MA",
      "score": 78.7,
      "shares": 16,
      "avg_cost": 508.4,
      "cost_basis": 8134.48,
      "current_price": 503.3,
      "current_value": 8052.8,
      "gain_loss": -81.68,
      "gain_pct": -1.0,
      "weight": 6.9,
      "target_weight": 7.14
    },
    {
      "ticker": "NOW",
      "score": 78.4,
      "shares": 81,
      "avg_cost": 103.57,
      "cost_basis": 8389.0,
      "current_price": 89.35,
      "current_value": 7237.35,
      "gain_loss": -1151.65,
      "gain_pct": -13.73,
      "weight": 6.2,
      "target_weight": 7.14
    },
    {
      "ticker": "AVGO",
      "score": 73.9,
      "shares": 25,
      "avg_cost": 332.23,
      "cost_basis": 8305.63,
      "current_price": 355.67,
      "current_value": 8891.75,
      "gain_loss": 586.12,
      "gain_pct": 7.06,
      "weight": 7.62,
      "target_weight": 7.14
    },
    {
      "ticker": "ADBE",
      "score": 73.8,
      "shares": 32,
      "avg_cost": 254.91,
      "cost_basis": 8157.0,
      "current_price": 228.33,
      "current_value": 7306.56,
      "gain_loss": -850.44,
      "gain_pct": -10.43,
      "weight": 6.26,
      "target_weight": 7.14
    },
    {
      "ticker": "MSFT",
      "score": 71.9,
      "shares": 21,
      "avg_cost": 493.44,
      "cost_basis": 10362.26,
      "current_price": 370.46,
      "current_value": 7779.66,
      "gain_loss": -2582.6,
      "gain_pct": -24.92,
      "weight": 6.67,
      "target_weight": 7.14
    },
    {
      "ticker": "GOOGL",
      "score": 71.5,
      "shares": 26,
      "avg_cost": 249.88,
      "cost_basis": 6497.0,
      "current_price": 318.33,
      "current_value": 8276.62,
      "gain_loss": 1779.62,
      "gain_pct": 27.39,
      "weight": 7.1,
      "target_weight": 7.14
    },
    {
      "ticker": "META",
      "score": 71.2,
      "shares": 12,
      "avg_cost": 746.88,
      "cost_basis": 8962.6,
      "current_price": 627.9,
      "current_value": 7534.8,
      "gain_loss": -1427.8,
      "gain_pct": -15.93,
      "weight": 6.46,
      "target_weight": 7.14
    },
    {
      "ticker": "CRM",
      "score": 69.1,
      "shares": 44,
      "avg_cost": 189.25,
      "cost_basis": 8327.0,
      "current_price": 169.68,
      "current_value": 7465.7,
      "gain_loss": -861.3,
      "gain_pct": -10.34,
      "weight": 6.4,
      "target_weight": 7.14
    },
    {
      "ticker": "AAPL",
      "score": 66.9,
      "shares": 30,
      "avg_cost": 273.47,
      "cost_basis": 8204.0,
      "current_price": 259.77,
      "current_value": 7793.1,
      "gain_loss": -410.9,
      "gain_pct": -5.01,
      "weight": 6.68,
      "target_weight": 7.14
    },
    {
      "ticker": "NFLX",
      "score": 66.7,
      "shares": 125,
      "avg_cost": 81.99,
      "cost_basis": 10248.22,
      "current_price": 102.11,
      "current_value": 12764.37,
      "gain_loss": 2516.15,
      "gain_pct": 24.55,
      "weight": 10.94,
      "target_weight": 7.14
    },
    {
      "ticker": "AMZN",
      "score": 63.3,
      "shares": 40,
      "avg_cost": 209.28,
      "cost_basis": 8371.0,
      "current_price": 231.47,
      "current_value": 9258.8,
      "gain_loss": 887.8,
      "gain_pct": 10.61,
      "weight": 7.94,
      "target_weight": 7.14
    }
  ]
}